<?xml version="1.0" encoding="UTF-8" standalone="no"?>
<songs>
  <song>
    <title>Fight Fire With Fire</title>
    <duration>360160</duration>
    <author>Metallica</author>
    <album>1999-07-24: Woodstock '99: Rome, NY, USA (disc 2)</album>
  </song>
  <song>
    <title>Nothing Else Matters</title>
    <duration>344560</duration>
    <author>Metallica</author>
    <album>1999-07-24: Woodstock '99: Rome, NY, USA (disc 2)</album>
  </song>
  <song>
    <title>Seek &amp; Destroy</title>
    <duration>434053</duration>
    <author>Metallica</author>
    <album>1999-07-24: Woodstock '99: Rome, NY, USA (disc 2)</album>
  </song>
</songs>
